LICENSE
MANIFEST.in
README.md
setup.py
pytest_github_report/__init__.py
pytest_github_report/plugin.py
pytest_github_report/version.py
pytest_github_report.egg-info/PKG-INFO
pytest_github_report.egg-info/SOURCES.txt
pytest_github_report.egg-info/dependency_links.txt
pytest_github_report.egg-info/entry_points.txt
pytest_github_report.egg-info/not-zip-safe
pytest_github_report.egg-info/requires.txt
pytest_github_report.egg-info/top_level.txt