Metadata-Version: 2.1
Name: pytest-github-report
Version: 0.0.1
Summary: Generate a GitHub report using pytest in GitHub Workflows
Home-page: https://github.com/vsoch/pytest-github-report
Author: Vanessa Sochat
Maintainer: Vanessa Sochat
License: LICENSE
Keywords: github,report,markdown,CI
Platform: UNKNOWN
Classifier: Development Status :: 4 - Beta
Classifier: Environment :: Plugins
Classifier: Framework :: Pytest
Classifier: Intended Audience :: Developers
Classifier: License :: OSI Approved :: Mozilla Public License 2.0 (MPL 2.0)
Classifier: Operating System :: OS Independent
Classifier: Programming Language :: Python :: 3
Classifier: Programming Language :: Python :: 3.6
Classifier: Programming Language :: Python :: 3.7
Classifier: Programming Language :: Python :: 3.8
Classifier: Programming Language :: Python :: 3.9
Classifier: Programming Language :: Python :: 3.10
Classifier: Programming Language :: Python :: 3 :: Only
Classifier: Programming Language :: Python :: Implementation :: CPython
Classifier: Programming Language :: Python :: Implementation :: PyPy
Classifier: Topic :: Software Development :: Testing
Classifier: Topic :: Text Processing
Classifier: Topic :: Text Processing :: Markup :: Markdown
Provides-Extra: all
License-File: LICENSE
